tail_jsonl/__init__.py
tail_jsonl/_private/__init__.py
tail_jsonl/_private/core.py
tail_jsonl/_runtime_type_check_setup.py
tail_jsonl/config.py
tail_jsonl/py.typed
tail_jsonl/scripts.py
tail_jsonl-1.4.2.dist-info/LICENSE
tail_jsonl-1.4.2.dist-info/METADATA
tail_jsonl-1.4.2.dist-info/WHEEL
tail_jsonl-1.4.2.dist-info/entry_points.txt
tail_jsonl-1.4.2.dist-info/RECORD
