Metadata-Version: 2.1
Name: tail_jsonl
Version: 1.4.2
Summary: Pretty Print Tailed JSONL Logs
Home-page: https://github.com/kyleking/tail-jsonl
License: MIT
Keywords: calcipy_template
Author: Kyle King
Author-email: dev.act.kyle@gmail.com
Requires-Python: >=3.9.13,<4.0.0
Classifier: Development Status :: 5 - Production/Stable
Classifier: License :: OSI Approved :: MIT License
Classifier: Operating System :: OS Independent
Classifier: Programming Language :: Python :: 3
Classifier: Programming Language :: Python :: 3.10
Classifier: Programming Language :: Python :: 3.11
Classifier: Programming Language :: Python :: 3.12
Classifier: Programming Language :: Python :: 3.13
Classifier: Programming Language :: Python :: 3.9
Requires-Dist: corallium (>=2.1.1)
Requires-Dist: dotted-notation (>=0.11.0)
Project-URL: Bug Tracker, https://github.com/kyleking/tail-jsonl/issues
Project-URL: Changelog, https://github.com/kyleking/tail-jsonl/blob/main/docs/docs/CHANGELOG.md
Project-URL: Documentation, https://tail-jsonl.kyleking.me
Project-URL: Repository, https://github.com/kyleking/tail-jsonl
